swd/__init__.py
swd/swd.py
swd-1.0.0.dist-info/LICENSE
swd-1.0.0.dist-info/METADATA
swd-1.0.0.dist-info/WHEEL
swd-1.0.0.dist-info/top_level.txt
swd-1.0.0.dist-info/RECORD
