Metadata-Version: 2.1
Name: swd
Version: 1.0.0
Summary: Simple Steam Workshop Downloader. Powered by MODSDOWNLOADER.COM
Home-page: https://github.com/DyadyushkaDyadya/swd
Author: modsdownloader
Author-email: nikitasss_2000@mail.ru
Project-URL: Documentation, https://github.com/DyadyushkaDyadya/swd#readme
Keywords: steam workshop downloader,swd,mods downloader,api
Classifier: Programming Language :: Python :: 3.11
Classifier: License :: OSI Approved :: MIT License
Requires-Python: >=3.7
License-File: LICENSE
Requires-Dist: requests (>=2.25.1)
